ChangeLog.rst
LICENSE
README.rst
setup.py
YOSO/Classes.py
YOSO/MainWindow.py
YOSO/Workspace.py
YOSO/__init__.py
YOSO.egg-info/PKG-INFO
YOSO.egg-info/SOURCES.txt
YOSO.egg-info/dependency_links.txt
YOSO.egg-info/entry_points.txt
YOSO.egg-info/requires.txt
YOSO.egg-info/top_level.txt