Metadata-Version: 1.1
Name: YOSO
Version: 0.1.1
Summary: You Only Show Once
Home-page: UNKNOWN
Author: Igor Pashev
Author-email: pashev.igor@gmail.com
License: WTFPL
Platform: UNKNOWN
Classifier: Development Status :: 3 - Alpha
Classifier: Environment :: X11 Applications :: Qt
Classifier: Intended Audience :: Science/Research
Classifier: License :: Public Domain
Classifier: Programming Language :: Python :: 3.5
Classifier: Topic :: Multimedia :: Graphics :: Viewers
Classifier: Topic :: Scientific/Engineering :: Visualization
Classifier: Topic :: Utilities
